pytest_cricri/__init__.py
pytest_cricri/plugin.py
pytest_cricri-1.0.dist-info/DESCRIPTION.rst
pytest_cricri-1.0.dist-info/METADATA
pytest_cricri-1.0.dist-info/RECORD
pytest_cricri-1.0.dist-info/WHEEL
pytest_cricri-1.0.dist-info/entry_points.txt
pytest_cricri-1.0.dist-info/metadata.json
pytest_cricri-1.0.dist-info/top_level.txt
