Metadata-Version: 2.0
Name: pytest-cricri
Version: 1.0
Summary: A Cricri plugin for pytest.
Home-page: UNKNOWN
Author: Vincent Maillol
Author-email: vincent.maillol@gmail.com
License: GPLv3
Platform: UNKNOWN
Classifier: Framework :: Pytest
Classifier: Topic :: Software Development :: Testing
Classifier: License :: OSI Approved :: GNU General Public License v3 (GPLv3)
Requires-Python: >=3.4
Requires-Dist: cricri
Requires-Dist: pytest
